{
	"welcomeFile": "index.html",
	"routes": [{
		"path": "/resources/com/dksh/announcments",
		"target": {
			"type": "application",
			"name": "DisplayAnnouncments"
		}
	}, {
		"path": "/resources",
		"target": {
			"type": "service",
			"name": "sapui5",
			"entryPath": "/resources"
		},
		"description": "SAPUI5 Resources"
	}, {
		"path": "/test-resources",
		"target": {
			"type": "service",
			"name": "sapui5",
			"entryPath": "/test-resources"
		},
		"description": "SAPUI5 Test Resources"
	}, {
		"path": "/IDPService",
		"target": {
			"type": "destination",
			"name": "IDPService"
		}
	}, {
		"path": "/XSJSAPI",
		"target": {
			"type": "destination",
			"name": "XSJSAPI"
		}
	}]
}